README.md
setup.py
urlshrink/ShortenerServer.py
urlshrink/__init__.py
urlshrink/__main__.py
urlshrink.egg-info/PKG-INFO
urlshrink.egg-info/SOURCES.txt
urlshrink.egg-info/dependency_links.txt
urlshrink.egg-info/entry_points.txt
urlshrink.egg-info/requires.txt
urlshrink.egg-info/top_level.txt
urlshrink/templates/base.html
urlshrink/templates/buttons.html
urlshrink/templates/delete.html
urlshrink/templates/input.html
urlshrink/templates/key.html
urlshrink/templates/login.html
urlshrink/templates/message.html
urlshrink/templates/modal.html
urlshrink/templates/navbar.html
urlshrink/templates/pfields.html
urlshrink/templates/qr.html
urlshrink/templates/search.html
urlshrink/templates/shorten.html
urlshrink/templates/signup.html
urlshrink/templates/statistics.html
urlshrink/templates/user.html