Metadata-Version: 2.1
Name: urlshrink
Version: 0.60
Summary: url smallifier
Home-page: https://github.com/nbdy/urlshrink
Author: Pascal Eberlein
Author-email: pascal@eberlein.io
License: UNKNOWN
Keywords: smoll url bean
Platform: UNKNOWN
Classifier: Development Status :: 3 - Alpha
Classifier: Intended Audience :: Developers
Classifier: Topic :: Software Development :: Build Tools
Classifier: License :: OSI Approved :: MIT License
Classifier: Programming Language :: Python :: 3
